setup.py
micropython_os.path.egg-info/PKG-INFO
micropython_os.path.egg-info/SOURCES.txt
micropython_os.path.egg-info/dependency_links.txt
micropython_os.path.egg-info/top_level.txt
os/path.py