Metadata-Version: 1.0
Name: micropython-os.path
Version: 0.0.3
Summary: os.path module for MicroPython
Home-page: https://github.com/micropython/micropython/issues/405
Author: MicroPython Developers
Author-email: micro-python@googlegroups.com
License: MIT
Platform: UNKNOWN
